dynlib/__init__.py
dynlib/cli.py
dynlib/errors.py
dynlib/mkdocs_helpers.py
dynlib/analysis/__init__.py
dynlib/analysis/basin.py
dynlib/analysis/basin_auto.py
dynlib/analysis/basin_codes.py
dynlib/analysis/basin_known.py
dynlib/analysis/basin_stats.py
dynlib/analysis/fixed_points.py
dynlib/analysis/manifold.py
dynlib/analysis/sweep.py
dynlib/analysis/post/__init__.py
dynlib/analysis/post/bifurcation.py
dynlib/analysis/post/trajectory.py
dynlib/compiler/__init__.py
dynlib/compiler/build.py
dynlib/compiler/guards.py
dynlib/compiler/mods.py
dynlib/compiler/paths.py
dynlib/compiler/codegen/__init__.py
dynlib/compiler/codegen/_runner_cache.py
dynlib/compiler/codegen/cache_importer.py
dynlib/compiler/codegen/emitter.py
dynlib/compiler/codegen/rewrite.py
dynlib/compiler/codegen/runner_cache.py
dynlib/compiler/codegen/runner_variants.py
dynlib/compiler/codegen/validate.py
dynlib/compiler/jit/__init__.py
dynlib/compiler/jit/cache.py
dynlib/compiler/jit/compile.py
dynlib/dsl/__init__.py
dynlib/dsl/astcheck.py
dynlib/dsl/constants.py
dynlib/dsl/parser.py
dynlib/dsl/schema.py
dynlib/dsl/spec.py
dynlib/models/__init__.py
dynlib/models/map/henon.toml
dynlib/models/map/henon2.toml
dynlib/models/map/ikeda.toml
dynlib/models/map/logistic.toml
dynlib/models/map/lozi.toml
dynlib/models/map/sine.toml
dynlib/models/map/standard.toml
dynlib/models/ode/duffing.toml
dynlib/models/ode/eto-circular.toml
dynlib/models/ode/exp-if.toml
dynlib/models/ode/expdecay.toml
dynlib/models/ode/fitzhugh-nagumo.toml
dynlib/models/ode/hodgkin-huxley.toml
dynlib/models/ode/izhikevich.toml
dynlib/models/ode/leaky-if.toml
dynlib/models/ode/lorenz.toml
dynlib/models/ode/quadratic-if.toml
dynlib/models/ode/resonate-if.toml
dynlib/models/ode/vanderpol.toml
dynlib/plot/__init__.py
dynlib/plot/_export.py
dynlib/plot/_facet.py
dynlib/plot/_fig.py
dynlib/plot/_primitives.py
dynlib/plot/_theme.py
dynlib/plot/basin.py
dynlib/plot/bifurcation.py
dynlib/plot/dynamics.py
dynlib/plot/vectorfield.py
dynlib-0.37.10.dist-info/licenses/LICENSE
dynlib-0.37.10.dist-info/METADATA
dynlib-0.37.10.dist-info/WHEEL
dynlib-0.37.10.dist-info/entry_points.txt
dynlib-0.37.10.dist-info/top_level.txt
dynlib-0.37.10.dist-info/RECORD
