Metadata-Version: 2.4
Name: dynlib
Version: 0.37.10
Summary: A dynamical systems simulation library.
Author-email: İsmail Öztürk <ismail.ozturk@amasya.edu.tr>
License-Expression: BSD-3-Clause
Keywords: ODE,dynamical-systems,simulation
Classifier: Development Status :: 3 - Alpha
Classifier: Intended Audience :: Science/Research
Classifier: Programming Language :: Python :: 3.10
Classifier: Topic :: Scientific/Engineering :: Mathematics
Requires-Python: >=3.10
License-File: LICENSE
Requires-Dist: numpy>=1.24
Provides-Extra: jit
Requires-Dist: numba>=0.57.1; extra == "jit"
Provides-Extra: plot
Requires-Dist: matplotlib>=3.7; extra == "plot"
Provides-Extra: dev
Requires-Dist: pytest>=7; extra == "dev"
Requires-Dist: scipy>=1.9; extra == "dev"
Requires-Dist: matplotlib>=3.7; extra == "dev"
Requires-Dist: numba>=0.57.1; extra == "dev"
Dynamic: license-file
